freestyle_keys/__init__.py
freestyle_keys/libre2.py
freestyle_keys/py.typed
freestyle_keys-1.0.1.dist-info/0BSD.txt
freestyle_keys-1.0.1.dist-info/AUTHORS
freestyle_keys-1.0.1.dist-info/METADATA
freestyle_keys-1.0.1.dist-info/MIT.txt
freestyle_keys-1.0.1.dist-info/WHEEL
freestyle_keys-1.0.1.dist-info/top_level.txt
freestyle_keys-1.0.1.dist-info/RECORD
