Metadata-Version: 2.1
Name: freestyle-keys
Version: 1.0.1
Summary: Cryptographic keys used by FreeStyle Libre 2 glucometers.
Home-page: https://github.com/glucometers-tech/freestyle-keys
Author: Diego Elio Pettenò
Author-email: flameeyes@flameeyes.com
License: Freely Distributable
Keywords: glucometer,diabetes,freestyle,abbott
Classifier: Development Status :: 4 - Beta
Classifier: Environment :: Plugins
Classifier: Intended Audience :: Developers
Classifier: License :: Freely Distributable
Classifier: Operating System :: OS Independent
Classifier: Programming Language :: Python
Classifier: Programming Language :: Python :: 3
Classifier: Topic :: Scientific/Engineering :: Medical Science Apps.
Requires-Python: ~=3.7
License-File: AUTHORS
License-File: LICENSES/0BSD.txt
License-File: LICENSES/MIT.txt
Provides-Extra: dev
Requires-Dist: mypy ; extra == 'dev'
Requires-Dist: pre-commit ; extra == 'dev'
Requires-Dist: pytest-mypy ; extra == 'dev'
Requires-Dist: setuptools-scm ; extra == 'dev'
